pineflow/readers/file/__init__.py
pineflow/readers/file/docx.py
pineflow/readers/file/html.py
pineflow/readers/file/json.py
pineflow/readers/file/pdf.py
pineflow_readers_file-0.7.1.dist-info/METADATA
pineflow_readers_file-0.7.1.dist-info/WHEEL
pineflow_readers_file-0.7.1.dist-info/RECORD
