Metadata-Version: 2.3
Name: pineflow-readers-file
Version: 0.7.1
Summary: pineflow readers file extension
License: MIT
Author: Leonardo Furnielis
Author-email: leonardofurnielis@outlook.com
Classifier: License :: OSI Approved :: MIT License
Classifier: Programming Language :: Python :: 2
Classifier: Programming Language :: Python :: 2.7
Classifier: Programming Language :: Python :: 3
Classifier: Programming Language :: Python :: 3.4
Classifier: Programming Language :: Python :: 3.5
Classifier: Programming Language :: Python :: 3.6
Classifier: Programming Language :: Python :: 3.7
Classifier: Programming Language :: Python :: 3.8
Classifier: Programming Language :: Python :: 3.9
Classifier: Programming Language :: Python :: 3.10
Classifier: Programming Language :: Python :: 3.11
Classifier: Programming Language :: Python :: 3.12
Classifier: Programming Language :: Python :: 3.13
Requires-Dist: beautifulsoup4 (>=4.13.4,<5.0.0)
Requires-Dist: docx2txt (>=0.9,<0.10)
Requires-Dist: jq (>=1.9.1,<2.0.0)
Requires-Dist: pineflow-core (>=0.7.2,<0.8.0)
Requires-Dist: pypdf (>=5.6.0,<6.0.0)
